freedata-0.17.3.dist-info/licenses/LICENSE
freedata_server/__init__.py
freedata_server/adif_udp_logger.py
freedata_server/api_validations.py
freedata_server/arq_data_type_handler.py
freedata_server/arq_session.py
freedata_server/arq_session_irs.py
freedata_server/arq_session_iss.py
freedata_server/audio.py
freedata_server/audio_buffer.py
freedata_server/codec2.py
freedata_server/codec2_filter_coeff.py
freedata_server/command.py
freedata_server/command_arq_raw.py
freedata_server/command_beacon.py
freedata_server/command_cq.py
freedata_server/command_fec.py
freedata_server/command_message_send.py
freedata_server/command_p2p_connection.py
freedata_server/command_ping.py
freedata_server/command_qrv.py
freedata_server/command_test.py
freedata_server/command_transmit_sine.py
freedata_server/config.py
freedata_server/constants.py
freedata_server/context.py
freedata_server/cw.py
freedata_server/data_frame_factory.py
freedata_server/demodulator.py
freedata_server/event_manager.py
freedata_server/exceptions.py
freedata_server/explorer.py
freedata_server/flrig.py
freedata_server/frame_dispatcher.py
freedata_server/frame_handler.py
freedata_server/frame_handler_arq_session.py
freedata_server/frame_handler_beacon.py
freedata_server/frame_handler_cq.py
freedata_server/frame_handler_p2p_connection.py
freedata_server/frame_handler_ping.py
freedata_server/helpers.py
freedata_server/list_ports_winreg.py
freedata_server/log_handler.py
freedata_server/maidenhead.py
freedata_server/message_p2p.py
freedata_server/message_system_db_attachments.py
freedata_server/message_system_db_beacon.py
freedata_server/message_system_db_manager.py
freedata_server/message_system_db_messages.py
freedata_server/message_system_db_model.py
freedata_server/message_system_db_station.py
freedata_server/modem.py
freedata_server/modem_frametypes.py
freedata_server/modulator.py
freedata_server/p2p_connection.py
freedata_server/radio_manager.py
freedata_server/rigctld.py
freedata_server/rigdummy.py
freedata_server/schedule_manager.py
freedata-0.17.3.dist-info/METADATA
freedata-0.17.3.dist-info/WHEEL
freedata-0.17.3.dist-info/entry_points.txt
freedata-0.17.3.dist-info/top_level.txt
freedata-0.17.3.dist-info/RECORD
