Metadata-Version: 2.4
Name: freedata
Version: 0.17.3
Summary: INFO: THIS PACKAGE IS NOT YET WORKING - PLEASE USE THE OFFICIAL SCRIPT BASED SETUP
Home-page: https://github.com/DJ2LS/FreeDATA
Author: DJ2LS
Author-email: dj2ls@proton.me
License: GPL3.0
Requires-Python: >=3.9
License-File: LICENSE
Requires-Dist: numpy
Requires-Dist: psutil
Requires-Dist: PyAudio
Requires-Dist: pyserial
Requires-Dist: sounddevice
Requires-Dist: structlog
Requires-Dist: requests
Requires-Dist: asyncio
Requires-Dist: chardet
Requires-Dist: colorama
Requires-Dist: ordered-set
Requires-Dist: nuitka<=2.7
Requires-Dist: pyinstaller
Requires-Dist: websocket-client
Requires-Dist: fastapi[standard]
Requires-Dist: uvicorn[standard]
Requires-Dist: autopep8
Requires-Dist: black
Requires-Dist: isort
Requires-Dist: pycodestyle
Requires-Dist: pytest
Requires-Dist: pytest-cov
Requires-Dist: pytest-cover
Requires-Dist: pytest-coverage
Requires-Dist: pytest-rerunfailures
Requires-Dist: pick
Requires-Dist: sqlalchemy
Dynamic: author
Dynamic: author-email
Dynamic: description
Dynamic: description-content-type
Dynamic: home-page
Dynamic: license
Dynamic: license-file
Dynamic: requires-dist
Dynamic: requires-python
Dynamic: summary
